MANIFEST.in
setup.py
htrc/.htrc.default
htrc/__init__.py
htrc/__main__.py
htrc/auth.py
htrc/config.py
htrc.egg-info/PKG-INFO
htrc.egg-info/SOURCES.txt
htrc.egg-info/dependency_links.txt
htrc.egg-info/entry_points.txt
htrc.egg-info/not-zip-safe
htrc.egg-info/requires.txt
htrc.egg-info/top_level.txt
htrc/lib/__init__.py
htrc/lib/cli.py
htrc/metadata/__init__.py
htrc/metadata/marc.py
htrc/mock/__init__.py
htrc/mock/volumes/__init__.py
htrc/mock/volumes/example.zip
htrc/tools/__init__.py
htrc/tools/mallet.py
htrc/tools/topicexplorer.py
htrc/util/__init__.py
htrc/util/resolve.py
htrc/volumes/__init__.py
htrc/workset/__init__.py
htrc/workset/__main__.py
htrc/workset/prov.py
tests/__init__.py
tests/test_htrc_auth.py
tests/test_htrc_config.py
tests/test_htrc_lib_cli.py
tests/test_htrc_mock_volumes.py
tests/test_htrc_util_resolve.py
tests/test_htrc_volumes.py
tests/test_htrc_workset.py