Metadata-Version: 1.1
Name: htrc
Version: 0.1.38
Summary: HathiTrust Research Center API Access
Home-page: http://analytics.hathitrust.org
Author: HathiTrust Research Center
Author-email: htrc@indiana.edu
License: UNKNOWN
Download-URL: http://github.com/htrc/HTRC-PythonSDK
Platform: UNKNOWN
Classifier: Programming Language :: Python
Classifier: Programming Language :: Python :: 2.7
Classifier: Programming Language :: Python :: 3.5
Classifier: Development Status :: 4 - Beta
Classifier: Intended Audience :: Science/Research
Classifier: License :: OSI Approved :: MIT License
Classifier: Operating System :: Unix
Classifier: Topic :: Scientific/Engineering :: Information Analysis
Classifier: Topic :: Software Development :: Libraries :: Python Modules
Classifier: Topic :: Text Processing :: Linguistic
